pysigfd/__init__.py
pysigfd/pysigfd.py
pysigfd/static.py
pysigfd-1.3.7.dist-info/LICENSE
pysigfd-1.3.7.dist-info/METADATA
pysigfd-1.3.7.dist-info/WHEEL
pysigfd-1.3.7.dist-info/top_level.txt
pysigfd-1.3.7.dist-info/RECORD
